torch_semiring_einsum/__init__.py
torch_semiring_einsum/equation.py
torch_semiring_einsum/extend.py
torch_semiring_einsum/function.py
torch_semiring_einsum/log_backward.py
torch_semiring_einsum/log_differentiable.py
torch_semiring_einsum/log_forward.py
torch_semiring_einsum/log_viterbi_forward.py
torch_semiring_einsum/py.typed
torch_semiring_einsum/real_backward.py
torch_semiring_einsum/real_differentiable.py
torch_semiring_einsum/real_forward.py
torch_semiring_einsum/utils.py
torch_semiring_einsum-1.2.0.dist-info/LICENSE
torch_semiring_einsum-1.2.0.dist-info/METADATA
torch_semiring_einsum-1.2.0.dist-info/WHEEL
torch_semiring_einsum-1.2.0.dist-info/RECORD
